orderbook.cp311-win_amd64.pyd
binancecpporderbookprototype-0.0.1.dist-info/METADATA
binancecpporderbookprototype-0.0.1.dist-info/WHEEL
binancecpporderbookprototype-0.0.1.dist-info/top_level.txt
binancecpporderbookprototype-0.0.1.dist-info/RECORD
