Metadata-Version: 2.4
Name: BinanceCPPOrderbookPrototype
Version: 0.0.1
Summary: Orderbook implementation using Pybind11 and C++
Home-page: https://www.youtube.com/watch?v=dQw4w9WgXcQ
Author: Daniel Lasota
Author-email: grossmann.root@gmail.com
Requires-Python: >=3.8
Requires-Dist: pybind11>=2.10.0
Dynamic: author
Dynamic: author-email
Dynamic: description
Dynamic: description-content-type
Dynamic: home-page
Dynamic: requires-dist
Dynamic: requires-python
Dynamic: summary
